slack_progress_bar_kjh/__init__.py
slack_progress_bar_kjh/slack_progress_bar_kjh.py
slack_progress_bar_kjh-1.1.1.dist-info/LICENSE
slack_progress_bar_kjh-1.1.1.dist-info/METADATA
slack_progress_bar_kjh-1.1.1.dist-info/WHEEL
slack_progress_bar_kjh-1.1.1.dist-info/top_level.txt
slack_progress_bar_kjh-1.1.1.dist-info/RECORD
