Metadata-Version: 2.1
Name: slack_progress_bar_kjh
Version: 1.1.1
Summary: Modify from Michael Lizzi's slack_progress_bar. Thank you.
Home-page: https://github.com/JaeHeong/slack-progress-bar_kjh
Author: jaehyeong.kim
Author-email: rlawogud970301@gmail.com
Classifier: Programming Language :: Python :: 3
Classifier: License :: OSI Approved :: MIT License
Classifier: Operating System :: OS Independent
Requires-Python: >=3.9
License-File: LICENSE
Requires-Dist: slack-sdk
